reffinder/__init__.py
reffinder/cli.py
reffinder/enums.py
reffinder/function.py
reffinder/langserver.py
reffinder/looped_sessions.py
reffinder/messages.py
reffinder/references.py
reffinder/response.py
reffinder/settings.py
reffinder/utils.py
reffinder-0.1.0.dist-info/LICENSE
reffinder-0.1.0.dist-info/METADATA
reffinder-0.1.0.dist-info/WHEEL
reffinder-0.1.0.dist-info/entry_points.txt
reffinder-0.1.0.dist-info/RECORD
