Metadata-Version: 2.3
Name: reffinder
Version: 0.1.0
Summary: A static reference-finder for Python functions using Pyright and the Language Server Protocol.
License: GNU General Public License v3 (GPLv3)
Keywords: python,reference,LSP,static-analysis,pyright,code-analysis
Author: Nikos
Author-email: n.lykotomaros@pivopt.com
Requires-Python: >=3.9
Classifier: License :: OSI Approved :: GNU General Public License v3 (GPLv3)
Classifier: License :: Other/Proprietary License
Classifier: Operating System :: OS Independent
Classifier: Programming Language :: Python :: 3
Classifier: Programming Language :: Python :: 3.9
Classifier: Programming Language :: Python :: 3.10
Classifier: Programming Language :: Python :: 3.11
Classifier: Programming Language :: Python :: 3.12
Classifier: Programming Language :: Python :: 3.13
Requires-Dist: graphviz (>=0.20.3,<0.21.0)
Requires-Dist: jsonrpcclient (==4.0.3)
